financeDA/__init__.py
financeDA/class_price_list.py
financeDA/class_stock_data.py
financeDA/class_stock_po.py
financeDA/functions_bsm.py
financeDA/functions_ffreg.py
financeDA/functions_single.py
financeDA/functions_stat.py
financeDA/functions_val.py
financeDA/functions_var.py
financeDA/main.py
financeDA/data/__init__.py
financeDA/data/ff_5factors_daily.csv
financeDA/data/stock_000651_19900101_20251219.csv
financeDA/data/stock_BABA_19900101_20251219.csv
financeDA/data/stock_close_2025.csv
financeda-0.3.1.dist-info/licenses/LICENSE
tests/__init__.py
tests/test_core.py
tests/test_local.py
financeda-0.3.1.dist-info/METADATA
financeda-0.3.1.dist-info/WHEEL
financeda-0.3.1.dist-info/top_level.txt
financeda-0.3.1.dist-info/RECORD
