Metadata-Version: 2.4
Name: financeDA
Version: 0.3.1
Summary: financial data analysis by brice.
Home-page: https://github.com/Brice2012/financeDA_python.git
Author: YeJunjie (nickname: Brice)
Author-email: ye@okwords.cn
Requires-Python: >=3.13.5
License-File: LICENSE
Requires-Dist: requests>=2.32.3
Requires-Dist: urllib3>=2.3.0
Requires-Dist: numpy>=2.1.3
Requires-Dist: pandas>=2.2.3
Requires-Dist: scipy>=1.15.3
Requires-Dist: pandas-datareader>=0.10.0
Requires-Dist: yfinance>=0.2.66
Requires-Dist: tushare>=1.4.24
Requires-Dist: matplotlib>=3.10.0
Requires-Dist: mplfinance>=0.12.10b0
Requires-Dist: scikit-learn>=1.6.1
Requires-Dist: statsmodels>=0.14.4
Requires-Dist: factor-analyzer>=0.5.1
Requires-Dist: pymysql>=1.1.2
Dynamic: license-file
